esroofit/__init__.py
esroofit/data_conversion.py
esroofit/exceptions.py
esroofit/resources.py
esroofit/roofit_manager.py
esroofit/roofit_models.py
esroofit/roofit_utils.py
esroofit/root_helper.py
esroofit/style.py
esroofit/version.py
esroofit/decorators/__init__.py
esroofit/decorators/histograms.py
esroofit/decorators/roofit.py
esroofit/lib/libesroofit.rootmap
esroofit/lib/libesroofit.so
esroofit/lib/libesroofit.so.1.0.0
esroofit/lib/libesroofit_rdict.pcm
esroofit/lib/esroofit/ABCDUtils.h
esroofit/lib/esroofit/DataUtils.h
esroofit/lib/esroofit/DrawUtils.h
esroofit/lib/esroofit/RhhNDKeysPdf.h
esroofit/lib/esroofit/RooABCDHistPdf.h
esroofit/lib/esroofit/RooBurr.h
esroofit/lib/esroofit/RooComplementCoef.h
esroofit/lib/esroofit/RooExpandedFitResult.h
esroofit/lib/esroofit/RooNonCentralBinning.h
esroofit/lib/esroofit/RooParamHistPdf.h
esroofit/lib/esroofit/RooTruncExponential.h
esroofit/lib/esroofit/RooWeibull.h
esroofit/lib/esroofit/Statistics.h
esroofit/lib/esroofit/TMsgLogger.h
esroofit/links/__init__.py
esroofit/links/add_propagated_error_to_roodataset.py
esroofit/links/convert_dataframe_2_roodataset.py
esroofit/links/convert_roodataset_2_dataframe.py
esroofit/links/convert_roodataset_2_roodatahist.py
esroofit/links/convert_root_hist_2_roodatahist.py
esroofit/links/convert_root_hist_2_roodataset.py
esroofit/links/print_ws.py
esroofit/links/read_from_root_file.py
esroofit/links/roodatahist_filler.py
esroofit/links/roofit_percentile_binning.py
esroofit/links/root_hist_filler.py
esroofit/links/trunc_exp_fit.py
esroofit/links/trunc_exp_gen.py
esroofit/links/uncorrelation_hypothesis_tester.py
esroofit/links/ws_utils.py
esroofit/tutorials/__init__.py
esroofit/tutorials/esk401_roothist_fill_plot_convert.py
esroofit/tutorials/esk402_roodatahist_fill.py
esroofit/tutorials/esk403_roodataset_convert.py
esroofit/tutorials/esk404_workspace_createpdf_simulate_fit_plot.py
esroofit/tutorials/esk405_simulation_based_on_binned_data.py
Eskapade_ROOT-0.9.0.dist-info/LICENSE
Eskapade_ROOT-0.9.0.dist-info/METADATA
Eskapade_ROOT-0.9.0.dist-info/NOTICE
Eskapade_ROOT-0.9.0.dist-info/WHEEL
Eskapade_ROOT-0.9.0.dist-info/top_level.txt
Eskapade_ROOT-0.9.0.dist-info/RECORD
