Metadata-Version: 2.1
Name: Eskapade-ROOT
Version: 0.9.0
Summary: Root for Eskapade
Home-page: http://eskapade.kave.io
Author: KPMG N.V. The Netherlands
Author-email: kave@kpmg.com
License: UNKNOWN
Platform: UNKNOWN
Requires-Python: >=3.5
Requires-Dist: eskapade (>=0.8.2)
Requires-Dist: root-numpy (>=4.7.3)
